samesite/__init__.py
samesite_checker-0.1.4.dist-info/LICENSE
samesite_checker-0.1.4.dist-info/METADATA
samesite_checker-0.1.4.dist-info/WHEEL
samesite_checker-0.1.4.dist-info/top_level.txt
samesite_checker-0.1.4.dist-info/RECORD
