Metadata-Version: 2.1
Name: samesite-checker
Version: 0.1.4
Summary: Samesite Checker
Home-page: UNKNOWN
Author: shujun.dsj
Author-email: dushujun9@gmail.com
License: UNKNOWN
Keywords: samesite
Platform: UNKNOWN
Classifier: Operating System :: MacOS
Classifier: Operating System :: POSIX
Classifier: Operating System :: POSIX :: Linux
Classifier: Programming Language :: Python
Classifier: Programming Language :: Python :: 3.5
Classifier: Programming Language :: Python :: 3.6
Classifier: Programming Language :: Python :: 3.7
Classifier: Programming Language :: Python :: 3.8
